README.md
setup.cfg
setup.py
AiohttpStarter/__init__.py
AiohttpStarter/__main__.py
AiohttpStarter/exceptions.py
AiohttpStarter/fileworker.py
AiohttpStarter.egg-info/PKG-INFO
AiohttpStarter.egg-info/SOURCES.txt
AiohttpStarter.egg-info/dependency_links.txt
AiohttpStarter.egg-info/requires.txt
AiohttpStarter.egg-info/top_level.txt
AiohttpStarter/core/__init__.py
AiohttpStarter/core/application_factory.py
AiohttpStarter/core/cli.py
AiohttpStarter/core/installs_exceptions.py