Metadata-Version: 1.1
Name: AiohttpStarter
Version: 0.2.4
Summary: Aiohttp server starter
Home-page: https://gitlab.com/maksimvrs/aiohttp-starter
Author: Maksim Vorontsov
Author-email: social.maksim.vrs@gmail.com
License: MIT
Download-URL: https://gitlab.com/maksimvrs/aiohttp-starter/-/archive/master/aiohttp-starter-master.tar.gz
Keywords: aiohttp,starter,django
Platform: UNKNOWN
Classifier: Development Status :: 3 - Alpha
Classifier: Intended Audience :: Developers
Classifier: Topic :: Software Development :: Build Tools
Classifier: License :: OSI Approved :: MIT License
Classifier: Programming Language :: Python :: 3
Classifier: Programming Language :: Python :: 3.4
Classifier: Programming Language :: Python :: 3.5
Classifier: Programming Language :: Python :: 3.6
Classifier: Programming Language :: Python :: 3.7
Classifier: Programming Language :: Python :: 3.8
